lokryn_mcp_log/__init__.py
lokryn_mcp_log/builder.py
lokryn_mcp_log/config.py
lokryn_mcp_log/proxy.py
lokryn_mcp_log/py.typed
lokryn_mcp_log/schema/__init__.py
lokryn_mcp_log/sinks/__init__.py
lokryn_mcp_log/sinks/base.py
lokryn_mcp_log/sinks/file.py
lokryn_mcp_log/sinks/http.py
lokryn_mcp_log/sinks/stdout.py
lokryn_mcp_log-0.4.0.dist-info/METADATA
lokryn_mcp_log-0.4.0.dist-info/WHEEL
lokryn_mcp_log-0.4.0.dist-info/licenses/LICENSE
lokryn_mcp_log-0.4.0.dist-info/RECORD
