Metadata-Version: 2.4
Name: lokryn-mcp-log
Version: 0.4.0
Summary: Compliance-grade audit logging for MCP client operations
Project-URL: Homepage, https://lokryn.com
Project-URL: Documentation, https://docs.lokryn.com/mcp-log
Project-URL: Repository, https://github.com/lokryn-llc/mcp-log
Project-URL: Issues, https://github.com/lokryn-llc/mcp-log/issues
Author-email: Lokryn LLC <oss@lokryn.com>
License-Expression: AGPL-3.0-only
License-File: LICENSE
Keywords: audit,compliance,hipaa,logging,mcp,soc2
Classifier: Development Status :: 4 - Beta
Classifier: Intended Audience :: Developers
Classifier: License :: OSI Approved :: GNU Affero General Public License v3
Classifier: Programming Language :: Python :: 3
Classifier: Programming Language :: Python :: 3.10
Classifier: Programming Language :: Python :: 3.11
Classifier: Programming Language :: Python :: 3.12
Classifier: Topic :: Security
Classifier: Topic :: System :: Logging
Requires-Python: >=3.10
Requires-Dist: aiofiles>=23.0.0
Requires-Dist: httpx>=0.25.0
Requires-Dist: lokryn-compliance-log>=0.2.0
Requires-Dist: mcp>=1.0.0
Provides-Extra: dev
Requires-Dist: pytest-asyncio>=0.21.0; extra == 'dev'
Requires-Dist: pytest>=7.0.0; extra == 'dev'
Requires-Dist: ruff>=0.1.0; extra == 'dev'
